{
  "audit_date": "2026-07-22T13:09:46.546863",
  "total_skills": 2097,
  "fix_mode": false,
  "fix_all": false,
  "by_severity": {
    "critical": 0,
    "warning": 0,
    "info": 0,
    "ok": 2097
  },
  "by_source": {
    "packaged": {
      "critical": 0,
      "warning": 0,
      "info": 0,
      "ok": 995
    },
    "differentiated/Agents": {
      "critical": 0,
      "warning": 0,
      "info": 0,
      "ok": 72
    },
    "differentiated/Automation": {
      "critical": 0,
      "warning": 0,
      "info": 0,
      "ok": 92
    },
    "differentiated/Communication": {
      "critical": 0,
      "warning": 0,
      "info": 0,
      "ok": 54
    },
    "differentiated/Creative": {
      "critical": 0,
      "warning": 0,
      "info": 0,
      "ok": 116
    },
    "differentiated/Development": {
      "critical": 0,
      "warning": 0,
      "info": 0,
      "ok": 89
    },
    "differentiated/Finance": {
      "critical": 0,
      "warning": 0,
      "info": 0,
      "ok": 21
    },
    "differentiated/Integrations": {
      "critical": 0,
      "warning": 0,
      "info": 0,
      "ok": 113
    },
    "differentiated/Knowledge": {
      "critical": 0,
      "warning": 0,
      "info": 0,
      "ok": 64
    },
    "differentiated/Lifestyle": {
      "critical": 0,
      "warning": 0,
      "info": 0,
      "ok": 36
    },
    "differentiated/Operations": {
      "critical": 0,
      "warning": 0,
      "info": 0,
      "ok": 27
    },
    "differentiated/Other": {
      "critical": 0,
      "warning": 0,
      "info": 0,
      "ok": 180
    },
    "differentiated/Productivity": {
      "critical": 0,
      "warning": 0,
      "info": 0,
      "ok": 78
    },
    "differentiated/Research": {
      "critical": 0,
      "warning": 0,
      "info": 0,
      "ok": 114
    },
    "differentiated/Security": {
      "critical": 0,
      "warning": 0,
      "info": 0,
      "ok": 46
    }
  },
  "critical_issues": [],
  "warning_issues": [],
  "info_issues": []
}